bitlyshortener/__init__.py
bitlyshortener/config.py
bitlyshortener/exc.py
bitlyshortener/shortener.py
bitlyshortener-0.6.4.dist-info/LICENSE
bitlyshortener-0.6.4.dist-info/METADATA
bitlyshortener-0.6.4.dist-info/WHEEL
bitlyshortener-0.6.4.dist-info/top_level.txt
bitlyshortener-0.6.4.dist-info/RECORD
