Metadata-Version: 2.1
Name: bitlyshortener
Version: 0.6.4
Summary: High-volume Bitly V4 URL shortener with memory-cache
Home-page: https://github.com/impredicative/bitlyshortener/
Author: Ouroboros Chrysopoeia
Author-email: impredicative@users.nomail.github.com
Keywords: bitly url shortener
Classifier: Programming Language :: Python :: 3.7
Classifier: Programming Language :: Python :: 3.8
Classifier: Programming Language :: Python :: 3.9
Classifier: Programming Language :: Python :: 3.10
Classifier: License :: OSI Approved :: GNU Affero General Public License v3
Classifier: Topic :: Internet :: WWW/HTTP
Classifier: Topic :: Software Development :: Libraries :: Python Modules
Requires-Python: >=3.7
License-File: LICENSE
Requires-Dist: cachetools (>=5.2.0)
Requires-Dist: requests (>=2.28.1)
